cherryadmin/__init__.py
cherryadmin/context.py
cherryadmin/handler.py
cherryadmin/sessions.py
cherryadmin/stats.py
cherryadmin/view.py
cherryadmin-5.21.1.dist-info/entry_points.txt
cherryadmin-5.21.1.dist-info/LICENSE
cherryadmin-5.21.1.dist-info/WHEEL
cherryadmin-5.21.1.dist-info/METADATA
cherryadmin-5.21.1.dist-info/RECORD
