Metadata-Version: 2.1
Name: cherryadmin
Version: 5.21.1
Summary: CherryPy admin framework
Home-page: https://github.com/martastain/cherryadmin
License: MIT
Keywords: admin,framework,web
Author: Martin Wacker
Author-email: martas@imm.cz
Requires-Python: >=3.6,<4.0
Classifier: Development Status :: 5 - Production/Stable
Classifier: Environment :: Console
Classifier: Intended Audience :: Developers
Classifier: License :: OSI Approved :: MIT License
Classifier: Natural Language :: English
Classifier: Operating System :: POSIX :: Linux
Classifier: Programming Language :: Python
Classifier: Programming Language :: Python :: 3
Classifier: Programming Language :: Python :: 3.6
Classifier: Programming Language :: Python :: 3.7
Classifier: Programming Language :: Python :: 3.8
Classifier: Programming Language :: Python :: 3.9
Requires-Dist: cherrypy (>=18.6,<19.0)
Requires-Dist: htmlmin (>=0.1.12,<0.2.0)
Requires-Dist: jinja2 (>=2.1,<3.0)
Requires-Dist: nxtools (>=1.6,<2.0)
Project-URL: Repository, https://github.com/martastain/cherryadmin
